<Mpeg7 xmlns:mpeg7="urn:mpeg:mpeg7:schema:2004">
  <MediaLocator>
    <MediaURI>331.jpg</MediaURI>
  </MediaLocator>
  <mpeg7:ColorStructureType>
    <Values> 37 0 0 0 0 0 0 132 50 10 0 0 0 0 0 0 10 12 0 0 0 0 94 56 45 27 17 23 14 16 2 1 94 106 118 57 61 55 51 46 52 47 32 39 121 98 28 18 158 169 132 48 63 62 64 45 118 94 82 90 100 39 41 46
</Values>
  </mpeg7:ColorStructureType>
  <mpeg7:ScalableColorType numOfBitPlanesDiscarded="0" numOfCoeff="128">
    <Coeff> -24 103 56 21 -1 -15 -2 30 -19 -44 -31 -17 9 14 19 22 -1 10 -3 5 -7 11 -10 12 -2 2 2 0 -3 5 1 -4 -1 0 1 -9 3 -1 1 5 0 0 -3 -7 -8 -5 0 5 1 0 2 2 2 3 3 0 0 0 0 -2 1 0 -3 -3 -1 0 0 0 1 -1 0 1 1 2 2 1 3 1 2 3 -2 -1 -3 -5 -1 -3 -3 0 3 1 2 1 -1 3 2 2 0 0 0 1 0 0 2 2 2 2 2 1 3 3 1 0 -1 0 0 1 0 0 1 0 1 1 1 0 1 0 -1 1
</Coeff>
  </mpeg7:ScalableColorType>
  <mpeg7:ColorLayoutType>
    <YDCCoeff>16</YDCCoeff>
    <CbDCCoeff>32</CbDCCoeff>
    <CrDCCoeff>40</CrDCCoeff>
    <YACCoeff63>25 23 25 17 15 13 16 18 15 21 17 17 15 17 17 16 18 15 12 15 17 17 11 18 15 17 15 15 16 15 17 16 15 14 16 16 16 17 16 16 16 16 17 16 17 16 18 16 16 16 15 17 15 15 17 16 16 16 16 17 16 16 15</YACCoeff63>
    <CbACCoeff27>17 19 19 17 18 16 16 17 16 18 16 15 15 16 16 16 16 16 16 16 15 16 15 17 16 16 16</CbACCoeff27>
    <CrACCoeff27>16 13 9 14 6 16 16 14 15 11 16 22 18 16 16 17 18 17 17 18 19 16 20 15 17 15 18</CrACCoeff27>
  </mpeg7:ColorLayoutType>
  <mpeg7:DominantColorType>
    <SpatialCoherency>5</SpatialCoherency>
    <Value>
      <Percentage>5</Percentage>
      <Index>1 2 2</Index>
      <ColorVariance>1 0 0</ColorVariance>
    </Value>
    <Value>
      <Percentage>3</Percentage>
      <Index>23 1 4</Index>
      <ColorVariance>0 1 0</ColorVariance>
    </Value>
    <Value>
      <Percentage>4</Percentage>
      <Index>19 22 24</Index>
      <ColorVariance>0 0 0</ColorVariance>
    </Value>
    <Value>
      <Percentage>6</Percentage>
      <Index>7 9 9</Index>
      <ColorVariance>0 0 0</ColorVariance>
    </Value>
    <Value>
      <Percentage>1</Percentage>
      <Index>11 2 3</Index>
      <ColorVariance>1 1 0</ColorVariance>
    </Value>
    <Value>
      <Percentage>1</Percentage>
      <Index>27 26 26</Index>
      <ColorVariance>0 1 0</ColorVariance>
    </Value>
    <Value>
      <Percentage>7</Percentage>
      <Index>16 16 16</Index>
      <ColorVariance>0 0 0</ColorVariance>
    </Value>
    <Value>
      <Percentage>1</Percentage>
      <Index>18 3 5</Index>
      <ColorVariance>1 1 0</ColorVariance>
    </Value>
  </mpeg7:DominantColorType>
  <mpeg7:HomogeneousTextureType>
    <Average>137</Average>
    <StandardDeviation>117</StandardDeviation>
    <Energy>223 223 196 176 203 219 196 185 169 153 164 172 174 166 143 148 124 140 147 129 127 137 126 110 147 138 142 125 135 125</Energy>
    <EnergyDeviation>223 225 194 175 206 220 184 179 163 148 157 165 161 159 127 135 110 135 138 106 122 119 120 107 133 114 116 111 105 111</EnergyDeviation>
  </mpeg7:HomogeneousTextureType>
  <mpeg7:EdgeHistogramType/>
  <BinCounts> 0 1 0 0 0 1 2 2 0 1 1 6 5 4 2 4 1 4 6 7 3 4 6 6 4 2 4 3 3 3 4 4 3 3 3 3 2 4 6 7 3 4 2 5 6 3 3 3 4 2 5 4 2 4 4 1 2 5 6 7 0 2 0 5 3 1 5 0 2 2 2 6 3 3 2 0 6 1 4 3
</BinCounts>
</Mpeg7>
